{
  "collectionName": "components_connectors_connectors",
  "info": {
    "name": "connectors",
    "icon": "anchor",
    "description": ""
  },
  "options": {},
  "attributes": {
    "name": {
      "type": "string"
    },
    "active": {
      "type": "boolean",
      "default": true
    },
    "mac_id": {
      "type": "string"
    },
    "charge": {
      "type": "float"
    },
    "status": {
      "type": "enumeration",
      "enum": [
        "CHARGING",
        "AVAILABLE",
        "UNAVAILABLE"
      ]
    }
  }
}
